visier/__init__.py
visier/sdk/__init__.py
visier/sdk/api/__init__.py
visier/sdk/api/data_intake/__init__.py
visier/sdk/api/data_intake/api_client.py
visier/sdk/api/data_intake/api_response.py
visier/sdk/api/data_intake/configuration.py
visier/sdk/api/data_intake/exceptions.py
visier/sdk/api/data_intake/py.typed
visier/sdk/api/data_intake/rest.py
visier/sdk/api/data_intake/api/__init__.py
visier/sdk/api/data_intake/api/data_intake_api.py
visier/sdk/api/data_intake/api/data_upload_api.py
visier/sdk/api/data_intake/models/__init__.py
visier/sdk/api/data_intake/models/data_transfer_result_detail.py
visier/sdk/api/data_intake/models/get_processing_jobs_response.py
visier/sdk/api/data_intake/models/google_protobuf_any.py
visier/sdk/api/data_intake/models/job.py
visier/sdk/api/data_intake/models/processing_job.py
visier/sdk/api/data_intake/models/push_data_cancel_response.py
visier/sdk/api/data_intake/models/push_data_column_definition_dto.py
visier/sdk/api/data_intake/models/push_data_complete_request.py
visier/sdk/api/data_intake/models/push_data_complete_response.py
visier/sdk/api/data_intake/models/push_data_response.py
visier/sdk/api/data_intake/models/push_data_source_definition_dto.py
visier/sdk/api/data_intake/models/push_data_source_definitions_dto.py
visier/sdk/api/data_intake/models/receiving_job_status_response.py
visier/sdk/api/data_intake/models/source.py
visier/sdk/api/data_intake/models/start_transfer_response.py
visier/sdk/api/data_intake/models/status.py
visier/sdk/api/data_intake/models/tenant.py
visier.sdk.api.data_intake-0.0.4.dist-info/METADATA
visier.sdk.api.data_intake-0.0.4.dist-info/WHEEL
visier.sdk.api.data_intake-0.0.4.dist-info/top_level.txt
visier.sdk.api.data_intake-0.0.4.dist-info/RECORD
