Metadata-Version: 2.1
Name: visier.sdk.api.data-intake
Version: 0.0.4
Summary: Visier Data Intake APIs
Home-page: UNKNOWN
Author: OpenAPI Generator community
Author-email: team@openapitools.org
License: Apache License, Version 2.0
Keywords: OpenAPI,OpenAPI-Generator,Visier Data Intake APIs
Platform: UNKNOWN
Requires-Dist: pydantic (>=2)
Requires-Dist: python-dateutil
Requires-Dist: typing-extensions (>=4.7.1)
Requires-Dist: urllib3 (<2.1.0,>=1.25.3)
